paygate/__init__.py
paygate/config.py
paygate/features.py
paygate/limits.py
paygate/models.py
paygate/paddle.py
paygate/py.typed
paygate-0.1.2.dist-info/licenses/LICENSE
paygate-0.1.2.dist-info/METADATA
paygate-0.1.2.dist-info/WHEEL
paygate-0.1.2.dist-info/top_level.txt
paygate-0.1.2.dist-info/RECORD
