Metadata-Version: 2.4
Name: paygate
Version: 0.1.2
Summary: Reusable subscription & feature gating library for FastAPI with Paddle integration
Author-email: Paygate Contributors <paygate@example.com>
License: MIT
Project-URL: Homepage, https://github.com/taladari/paygate
Project-URL: Repository, https://github.com/taladari/paygate
Project-URL: Issues, https://github.com/taladari/paygate/issues
Project-URL: Documentation, https://github.com/taladari/paygate#readme
Keywords: subscription,feature-gating,paddle,fastapi,saas
Classifier: Development Status :: 3 - Alpha
Classifier: Intended Audience :: Developers
Classifier: License :: OSI Approved :: MIT License
Classifier: Programming Language :: Python :: 3
Classifier: Programming Language :: Python :: 3.8
Classifier: Programming Language :: Python :: 3.9
Classifier: Programming Language :: Python :: 3.10
Classifier: Programming Language :: Python :: 3.11
Classifier: Programming Language :: Python :: 3.12
Classifier: Framework :: FastAPI
Requires-Python: >=3.8
License-File: LICENSE
Requires-Dist: fastapi>=0.100.0
Requires-Dist: sqlalchemy>=2.0.0
Requires-Dist: pydantic>=2.0.0
Requires-Dist: httpx>=0.24.0
Requires-Dist: python-multipart>=0.0.6
Provides-Extra: dev
Requires-Dist: pytest>=7.0.0; extra == "dev"
Requires-Dist: pytest-asyncio>=0.21.0; extra == "dev"
Requires-Dist: pytest-mock>=3.10.0; extra == "dev"
Requires-Dist: black>=23.0.0; extra == "dev"
Requires-Dist: isort>=5.12.0; extra == "dev"
Requires-Dist: flake8>=6.0.0; extra == "dev"
Requires-Dist: mypy>=1.0.0; extra == "dev"
Dynamic: license-file
